autodl/__init__.py
autodl/__version__.py
autodl/benchmark/__init__.py
autodl/benchmark/opendl.py
autodl/benchmark/server.py
autodl/callback/__init__.py
autodl/callback/_base_callback.py
autodl/callback/budget_estimator_callback.py
autodl/callback/logger_callback.py
autodl/cli/__init__.py
autodl/cli/bench.py
autodl/cli/cli.py
autodl/cli/dataset.py
autodl/core/__init__.py
autodl/core/logging.py
autodl/core/run.py
autodl/core/ingestion/__init__.py
autodl/core/ingestion/ingestion.py
autodl/core/scoring/__init__.py
autodl/core/scoring/libscores.py
autodl/core/scoring/matrix.py
autodl/core/scoring/score.py
autodl/data/__init__.py
autodl/data/_data_bundle.py
autodl/data/_dataset.py
autodl/data/data_browser.py
autodl/data/data_converter.py
autodl/data/data_io.py
autodl/data/data_pb2.py
autodl/data/dataset_utils.py
autodl/data/urls.py
autodl/data/utils.py
autodl/metric/__init__.py
autodl/metric/_metric.py
autodl/model/__init__.py
autodl/model/learner/__init__.py
autodl/model/learner/_learner.py
autodl/model/metalearner/__init__.py
autodl/model/metalearner/_meta_learner.py
autodl/model/predictor/__init__.py
autodl/model/predictor/_constant.py
autodl/model/predictor/_predictor.py
autodl/resource/__init__.py
autodl/resource/_resource.py
autodl/task/__init__.py
autodl/task/_meta_task.py
autodl/task/_task.py
autodl/utils/__init__.py
autodl/utils/tf_utils.py
autodl/utils/training_time.py
autodl/workflow/__init__.py
autodl/workflow/_base_learning_workflow.py
autodl/workflow/_workflow.py
autodl/workflow/util.py
autodl-0.0.1.dist-info/METADATA
autodl-0.0.1.dist-info/WHEEL
autodl-0.0.1.dist-info/entry_points.txt
autodl-0.0.1.dist-info/top_level.txt
autodl-0.0.1.dist-info/RECORD
