Metadata-Version: 2.1
Name: autodl
Version: 0.0.1
Summary: UNKNOWN
Home-page: UNKNOWN
License: BSD-2
Platform: UNKNOWN
Classifier: Development Status :: 3 - Alpha
Classifier: Programming Language :: Python
Classifier: Programming Language :: Python :: 3
Classifier: Programming Language :: Python :: 3.7
Requires-Python: >=3.5
Requires-Dist: numpy
Requires-Dist: scikit-learn
Requires-Dist: tqdm
Requires-Dist: tensorflow (>=2.0.0)
Requires-Dist: torch (>=1.3.0)
Requires-Dist: keras
Requires-Dist: pandas (>=0.25.0)
Requires-Dist: matplotlib (>=3.1.0)
Requires-Dist: psutil (==5.6.7)
Provides-Extra: dev
Requires-Dist: twine ; extra == 'dev'
